LICENSE.md
MANIFEST.in
README.rst
requirements.txt
setup.cfg
setup.py
paystack/__init__.py
paystack/client.py
paystack/error.py
paystack/resource.py
paystack/util.py
paystack/version.py
paystack.egg-info/PKG-INFO
paystack.egg-info/SOURCES.txt
paystack.egg-info/dependency_links.txt
paystack.egg-info/requires.txt
paystack.egg-info/top_level.txt
paystack/data/.DS_Store
paystack/data/paystack.crt
paystack/data/paystack.key
paystack/data/server.csr