Metadata-Version: 1.1
Name: paystack
Version: 1.3.0
Summary: A Paystack API wrapper in Python
Home-page: https://github.com/ojengwa/paystack
Author: Bernard Ojengwa
Author-email: bernardojengwa@gmail.com
License: BSD
Download-URL: https://github.com/ojengwa/paystack/tarball/1.3.0
Platform: UNKNOWN
Classifier: Development Status :: 5 - Production/Stable
Classifier: Intended Audience :: Developers
Classifier: Topic :: Software Development :: Libraries
Classifier: Programming Language :: Python :: 2
Classifier: Programming Language :: Python :: 2.6
Classifier: Programming Language :: Python :: 2.7
Classifier: Programming Language :: Python :: 3
Classifier: Programming Language :: Python :: 3.2
Classifier: Programming Language :: Python :: 3.3
Classifier: Programming Language :: Python :: 3.4
Classifier: Programming Language :: Python :: 3.5
